Metadata-Version: 1.0
Name: simple-anomaly
Version: 0.1
Summary: Anomaly detection
Home-page: UNKNOWN
Author: UNKNOWN
Author-email: rodrigosannn@gmail.com
License: UNKNOWN
Platform: UNKNOWN
